qwiic_opt4048.py
sparkfun_opt4048_tristimulus_color_sensor-1.0.0.dist-info/LICENSE
sparkfun_opt4048_tristimulus_color_sensor-1.0.0.dist-info/METADATA
sparkfun_opt4048_tristimulus_color_sensor-1.0.0.dist-info/WHEEL
sparkfun_opt4048_tristimulus_color_sensor-1.0.0.dist-info/top_level.txt
sparkfun_opt4048_tristimulus_color_sensor-1.0.0.dist-info/RECORD
