Metadata-Version: 2.1
Name: sparkfun-opt4048-tristimulus-color-sensor
Version: 1.0.0
Summary: SparkFun Electronics Tristiumulus Color Sensor - OPT4048
Home-page: https://www.sparkfun.com/products/22638
Author: SparkFun Electronics
Author-email: info@sparkfun.com
License: MIT
Keywords: electronics,maker,sensing
Platform: UNKNOWN
Classifier: Development Status :: 5 - Production/Stable
Classifier: Intended Audience :: Developers
Classifier: Topic :: Software Development :: Build Tools
Classifier: License :: OSI Approved :: MIT License
Classifier: Programming Language :: Python :: 3.10
Classifier: Programming Language :: Python :: 3.11
License-File: LICENSE
